entropies/__init__.py
entropies/main.py
entropies-0.2.dist-info/LICENSE.txt
entropies-0.2.dist-info/METADATA
entropies-0.2.dist-info/WHEEL
entropies-0.2.dist-info/top_level.txt
entropies-0.2.dist-info/RECORD
