Metadata-Version: 2.1
Name: entropies
Version: 0.2
Summary: UNKNOWN
Home-page: UNKNOWN
Author: Yeison Cardona
Author-email: yencardonaal@unal.edu.co
Maintainer: Yeison Cardona
Maintainer-email: yencardonaal@unal.edu.co
License: Simplified BSD License
Platform: UNKNOWN
Classifier: Development Status :: 4 - Beta
Classifier: Intended Audience :: Developers
Classifier: Intended Audience :: Education
Classifier: Intended Audience :: Healthcare Industry
Classifier: Intended Audience :: Science/Research
Classifier: License :: OSI Approved :: BSD License
Classifier: Programming Language :: Python :: 3.7
Classifier: Programming Language :: Python :: 3.8
Classifier: Topic :: Scientific/Engineering
Classifier: Topic :: Scientific/Engineering :: Artificial Intelligence
Classifier: Topic :: Scientific/Engineering :: Human Machine Interfaces
Classifier: Topic :: Scientific/Engineering :: Medical Science Apps.
Classifier: Topic :: Software Development :: Embedded Systems
Classifier: Topic :: Software Development :: Libraries
Classifier: Topic :: Software Development :: Libraries :: Application Frameworks
Classifier: Topic :: Software Development :: Libraries :: Python Modules
Classifier: Topic :: System :: Hardware :: Hardware Drivers
Requires-Python: >=3.6
Requires-Dist: numpy
Requires-Dist: scipy
